como/__init__.py
como/battery.py
como/cli.py
como/core.py
como/help.py
como/settings.py
como-0.7.0.dist-info/LICENSE
como-0.7.0.dist-info/METADATA
como-0.7.0.dist-info/WHEEL
como-0.7.0.dist-info/entry_points.txt
como-0.7.0.dist-info/top_level.txt
como-0.7.0.dist-info/RECORD
