Metadata-Version: 2.1
Name: como
Version: 0.7.0
Summary: como: batteries complete
Home-page: https://github.com/cwoebker/como
Author: cwoebker
Author-email: me@cwoebker.com
License: BSD
Platform: UNKNOWN
Classifier: License :: OSI Approved :: BSD License
Classifier: Environment :: Console
Classifier: Natural Language :: English
Classifier: Intended Audience :: Developers
Classifier: Operating System :: OS Independent
Classifier: Topic :: Software Development
Classifier: Topic :: Terminals
Classifier: Topic :: Utilities
Classifier: Topic :: Text Processing
Classifier: Programming Language :: Python
Classifier: Programming Language :: Python :: 2.7
Classifier: Programming Language :: Python :: Implementation :: CPython
Classifier: Programming Language :: Python :: Implementation :: PyPy
Requires-Python: >=2.7.0
Requires-Dist: paxo
Requires-Dist: python-dateutil
Requires-Dist: python-crontab
Requires-Dist: tablib
Requires-Dist: requests
